lowclouds/__init__.py
lowclouds/bq.py
lowclouds/gcs.py
lowclouds/s3.py
lowclouds-0.1.2.dist-info/LICENSE
lowclouds-0.1.2.dist-info/WHEEL
lowclouds-0.1.2.dist-info/METADATA
lowclouds-0.1.2.dist-info/RECORD
