Metadata-Version: 2.1
Name: lowclouds
Version: 0.1.2
Summary: The lowclouds is a shortcut library for several cloud service libraries.
License: Apache-2.0
Author: rhoboro
Author-email: rhoboro@gmail.com
Requires-Python: >=3.7,<4.0
Classifier: License :: OSI Approved :: Apache Software License
Classifier: Programming Language :: Python :: 3
Classifier: Programming Language :: Python :: 3.7
Classifier: Programming Language :: Python :: 3.8
Provides-Extra: bigquery
Provides-Extra: gcs
Provides-Extra: s3
Requires-Dist: boto3 (>=1.14.55,<2.0.0); extra == "s3"
Requires-Dist: google-cloud-bigquery (>=1.27.2,<2.0.0); extra == "bigquery"
Requires-Dist: google-cloud-bigquery-storage (>=1.0.0,<2.0.0); extra == "bigquery"
Requires-Dist: google-cloud-storage (>=1.31.0,<2.0.0); extra == "gcs"
Requires-Dist: grpcio (>=1.31.0,<2.0.0); extra == "bigquery"
